{
  "id": "9c6fd028-e558-4446-9dfb-5661e4b30961",
  "nome": "Smith Machine Hip Raise",
  "grupoMuscular": [
    "abdominals"
  ],
  "grupoMuscularSecundario": [],
  "nivel": "beginner",
  "tipo": "pull",
  "mecanica": "isolation",
  "categoria": null,
  "instrucoes": [
    "Position a bench in the rack and load the bar to an appropriate weight. Lie down on the bench, placing the bottom of your feet against the bar. Unlock the bar and extend your legs. You may need to use your hands to assist you. For added stability grasp the sides of the Smith Machine. This will be your starting position.",
    "Initiate the movement by rotating your pelvis, flexing your spine to raise your hips off of the bench. Maintain a slight bend in the knees throughout the motion.",
    "After a brief pause, return the hips to the bench.",
    "Repeat for the desired number of repetitions."
  ],
  "imagens": [
    "C:/Users/lino/Projetos_Programa\u00E7\u00E3o/gym-companion/assats/exercisesDB/Smith_Machine_Hip_Raise\\images\\0.jpg",
    "C:/Users/lino/Projetos_Programa\u00E7\u00E3o/gym-companion/assats/exercisesDB/Smith_Machine_Hip_Raise\\images\\1.jpg"
  ]
}